gdparser/__init__.py
gdparser/parser.py
gdparser/__pycache__/__init__.cpython-37.pyc
gdparser/__pycache__/parser.cpython-37.pyc
gdparser/__pycache__/test.cpython-37-pytest-5.2.1.pyc
gdparser-0.0.2.dist-info/LICENSE
gdparser-0.0.2.dist-info/METADATA
gdparser-0.0.2.dist-info/WHEEL
gdparser-0.0.2.dist-info/top_level.txt
gdparser-0.0.2.dist-info/RECORD
