Metadata-Version: 2.1
Name: gdparser
Version: 0.0.2
Summary: Google Docstring Parser
Home-page: https://github.com/broaddeep/gdparser.git
Author: broaddeep
Author-email: broaddeep@gmail.com
License: Apache
Keywords: parser docstring google text
Platform: UNKNOWN
Classifier: Intended Audience :: Science/Research
Classifier: License :: OSI Approved :: Apache Software License
Classifier: Programming Language :: Python :: 3
Requires-Python: >=3.6.0
